gurobipy-stubs/__init__.pyi
gurobipy-stubs/gurobipy.pyi
gurobipy_stubs-2.0.0.dist-info/LICENSE.txt
gurobipy_stubs-2.0.0.dist-info/METADATA
gurobipy_stubs-2.0.0.dist-info/WHEEL
gurobipy_stubs-2.0.0.dist-info/top_level.txt
gurobipy_stubs-2.0.0.dist-info/RECORD
