Metadata-Version: 2.1
Name: gurobipy-stubs
Version: 2.0.0
Summary: Type stubs for gurobipy
Home-page: https://www.gurobi.com
Author: Gurobi Optimization, LLC
License: MIT
License-File: LICENSE.txt
Requires-Dist: gurobipy (==10.*)
